galaxy/engine/__init__.py
galaxy/engine/backtest/__init__.py
galaxy/engine/backtest/backtest.py
galaxy/engine/constant.py
galaxy/engine/engine.py
galaxy/engine/ml/__init__.py
galaxy/engine/ml/cluster.py
galaxy/engine/ml/comp.py
galaxy/engine/ml/feat.py
galaxy/engine/ml/hyperparam.py
galaxy/engine/ml/pred.py
galaxy/engine/pl/__init__.py
galaxy/engine/pl/pl.py
galaxy/engine/pricing/__init__.py
galaxy/engine/pricing/bs.py
galaxy/engine/pricing/mc.py
galaxy/engine/risk/__init__.py
galaxy/engine/risk/risk.py
galaxy/engine/vol/__init__.py
galaxy/engine/vol/polyvol.py
galaxy/engine/vol/vol.py
galaxy_py_engine-0.0.2.dist-info/AUTHORS
galaxy_py_engine-0.0.2.dist-info/COPYING.md
galaxy_py_engine-0.0.2.dist-info/LICENSE.txt
galaxy_py_engine-0.0.2.dist-info/METADATA
galaxy_py_engine-0.0.2.dist-info/WHEEL
galaxy_py_engine-0.0.2.dist-info/RECORD
